{
  "project_info": {
    "project_number": "894155655354",
    "firebase_url": "https://phoneauth-acbb5.firebaseio.com",
    "project_id": "phoneauth-acbb5",
    "storage_bucket": "phoneauth-acbb5.appspot.com"
  },
  "client": [
    {
      "client_info": {
        "mobilesdk_app_id": "1:894155655354:android:cd641e882efefd7e971a83",
        "android_client_info": {
          "package_name": "com.example.otp_phone"
        }
      },
      "oauth_client": [
        {
          "client_id": "894155655354-bupke0l52h4ukj4omiv8p0kkh1pirver.apps.googleusercontent.com",
          "client_type": 1,
          "android_info": {
            "package_name": "com.example.otp_phone",
            "certificate_hash": "53e1b525f371d405131fd794e7e69ec6824d68b8"
          }
        },
        {
          "client_id": "894155655354-sbul0vvmscb8804vl70pfkhipctg9cm5.apps.googleusercontent.com",
          "client_type": 3
        }
      ],
      "api_key": [
        {
          "current_key": "AIzaSyCVGTznzGc9oKxSS0zxeaXqLPaTfU8Fkjk"
        }
      ],
      "services": {
        "appinvite_service": {
          "other_platform_oauth_client": [
            {
              "client_id": "894155655354-sbul0vvmscb8804vl70pfkhipctg9cm5.apps.googleusercontent.com",
              "client_type": 3
            }
          ]
        }
      }
    },
    {
      "client_info": {
        "mobilesdk_app_id": "1:894155655354:android:38dd1dfef20d1afa971a83",
        "android_client_info": {
          "package_name": "com.example.page1"
        }
      },
      "oauth_client": [
        {
          "client_id": "894155655354-sbul0vvmscb8804vl70pfkhipctg9cm5.apps.googleusercontent.com",
          "client_type": 3
        }
      ],
      "api_key": [
        {
          "current_key": "AIzaSyCVGTznzGc9oKxSS0zxeaXqLPaTfU8Fkjk"
        }
      ],
      "services": {
        "appinvite_service": {
          "other_platform_oauth_client": [
            {
              "client_id": "894155655354-sbul0vvmscb8804vl70pfkhipctg9cm5.apps.googleusercontent.com",
              "client_type": 3
            }
          ]
        }
      }
    },
    {
      "client_info": {
        "mobilesdk_app_id": "1:894155655354:android:094670dbcbbd3839971a83",
        "android_client_info": {
          "package_name": "com.example.phonenumberverification"
        }
      },
      "oauth_client": [
        {
          "client_id": "894155655354-6bgjkdo2ed7qo97mihu32c4k1321qf88.apps.googleusercontent.com",
          "client_type": 1,
          "android_info": {
            "package_name": "com.example.phonenumberverification",
            "certificate_hash": "53e1b525f371d405131fd794e7e69ec6824d68b8"
          }
        },
        {
          "client_id": "894155655354-sbul0vvmscb8804vl70pfkhipctg9cm5.apps.googleusercontent.com",
          "client_type": 3
        }
      ],
      "api_key": [
        {
          "current_key": "AIzaSyCVGTznzGc9oKxSS0zxeaXqLPaTfU8Fkjk"
        }
      ],
      "services": {
        "appinvite_service": {
          "other_platform_oauth_client": [
            {
              "client_id": "894155655354-sbul0vvmscb8804vl70pfkhipctg9cm5.apps.googleusercontent.com",
              "client_type": 3
            }
          ]
        }
      }
    },
    {
      "client_info": {
        "mobilesdk_app_id": "1:894155655354:android:19c524c610af99da971a83",
        "android_client_info": {
          "package_name": "com.example.phoneotp"
        }
      },
      "oauth_client": [
        {
          "client_id": "894155655354-6ipppsqhdq0amd97rfsb8vbvitvafeu0.apps.googleusercontent.com",
          "client_type": 1,
          "android_info": {
            "package_name": "com.example.phoneotp",
            "certificate_hash": "53e1b525f371d405131fd794e7e69ec6824d68b8"
          }
        },
        {
          "client_id": "894155655354-sbul0vvmscb8804vl70pfkhipctg9cm5.apps.googleusercontent.com",
          "client_type": 3
        }
      ],
      "api_key": [
        {
          "current_key": "AIzaSyCVGTznzGc9oKxSS0zxeaXqLPaTfU8Fkjk"
        }
      ],
      "services": {
        "appinvite_service": {
          "other_platform_oauth_client": [
            {
              "client_id": "894155655354-sbul0vvmscb8804vl70pfkhipctg9cm5.apps.googleusercontent.com",
              "client_type": 3
            }
          ]
        }
      }
    },
    {
      "client_info": {
        "mobilesdk_app_id": "1:894155655354:android:77da7f3cbf08417c971a83",
        "android_client_info": {
          "package_name": "net.smallacademy.otpauth"
        }
      },
      "oauth_client": [
        {
          "client_id": "894155655354-8ccfif3cgr0ct6dqb817ei0e1q67pnt6.apps.googleusercontent.com",
          "client_type": 1,
          "android_info": {
            "package_name": "net.smallacademy.otpauth",
            "certificate_hash": "53e1b525f371d405131fd794e7e69ec6824d68b8"
          }
        },
        {
          "client_id": "894155655354-sbul0vvmscb8804vl70pfkhipctg9cm5.apps.googleusercontent.com",
          "client_type": 3
        }
      ],
      "api_key": [
        {
          "current_key": "AIzaSyCVGTznzGc9oKxSS0zxeaXqLPaTfU8Fkjk"
        }
      ],
      "services": {
        "appinvite_service": {
          "other_platform_oauth_client": [
            {
              "client_id": "894155655354-sbul0vvmscb8804vl70pfkhipctg9cm5.apps.googleusercontent.com",
              "client_type": 3
            }
          ]
        }
      }
    }
  ],
  "configuration_version": "1"
}